nimo/__init__.py
nimo/nimo_modules.py
nimo/ai_tools/ai_tool_blox.py
nimo/ai_tools/ai_tool_bomp.py
nimo/ai_tools/ai_tool_combi.py
nimo/ai_tools/ai_tool_doe.py
nimo/ai_tools/ai_tool_es.py
nimo/ai_tools/ai_tool_nts.py
nimo/ai_tools/ai_tool_pdc.py
nimo/ai_tools/ai_tool_physbo.py
nimo/ai_tools/ai_tool_ptr.py
nimo/ai_tools/ai_tool_re.py
nimo/ai_tools/ai_tool_rsvm.py
nimo/ai_tools/ai_tool_slesa.py
nimo/ai_tools/ai_tool_slesa_WAM.py
nimo/input_tools/preparation_input_certus.py
nimo/input_tools/preparation_input_certus_sc.py
nimo/input_tools/preparation_input_combat.py
nimo/input_tools/preparation_input_naree.py
nimo/input_tools/preparation_input_standard.py
nimo/output_tools/analysis_output_combat.py
nimo/output_tools/analysis_output_naree.py
nimo/output_tools/analysis_output_sd8.py
nimo/output_tools/analysis_output_standard.py
nimo/output_tools/analysis_output_update.py
nimo/visualization/plot_distribution.py
nimo/visualization/plot_history.py
nimo/visualization/plot_phase_diagram.py
nimo-2.1.0.dist-info/METADATA
nimo-2.1.0.dist-info/WHEEL
nimo-2.1.0.dist-info/top_level.txt
nimo-2.1.0.dist-info/RECORD
