Metadata-Version: 2.4
Name: nimo
Version: 2.1.0
Summary: NIMO package
Author: NIMO developers
License-Expression: MIT
Requires-Dist: matplotlib
Requires-Dist: numpy
Requires-Dist: physbo>=3.1.0
Requires-Dist: scikit-learn
Requires-Dist: scipy
Requires-Dist: pyDOE3
